chattermark/__init__.py
chattermark/gpt_chat_cli.py
chattermark/gpt_chat_model.py
chattermark/gpt_chat_to_md.py
chattermark-0.1.0.dist-info/METADATA
chattermark-0.1.0.dist-info/WHEEL
chattermark-0.1.0.dist-info/entry_points.txt
chattermark-0.1.0.dist-info/RECORD
