Metadata-Version: 2.1
Name: chattermark
Version: 0.1.0
Summary: A fun and easy-to-use command-line application that converts GPT chat sessions into beautifully formatted Markdown files.
License: MIT
Author: Christian Fobel
Author-email: christian@fobel.net
Requires-Python: >=3.11,<4.0
Classifier: License :: OSI Approved :: MIT License
Classifier: Programming Language :: Python :: 3
Classifier: Programming Language :: Python :: 3.11
Requires-Dist: pydantic (>=1,<2)
Requires-Dist: rich (>=12,<13)
Requires-Dist: typer (>=0,<1)
